phoebusgen/__init__.py
phoebusgen/_shared_property_helpers.py
phoebusgen/_version.py
phoebusgen/_version.pyi
phoebusgen/config/4.7.1_widgets.def
phoebusgen/config/4.7.2_widgets.def
phoebusgen/config/4.7.3_widgets.def
phoebusgen/config/4.7_widgets.def
phoebusgen/config/classes.bcf
phoebusgen/config/color.def
phoebusgen/config/font.def
phoebusgen/screen/__init__.py
phoebusgen/screen/screen.py
phoebusgen/widget/__init__.py
phoebusgen/widget/colors.yaml
phoebusgen/widget/fonts.yaml
phoebusgen/widget/properties.py
phoebusgen/widget/widget.py
phoebusgen/widget/widgets.py
phoebusgen-3.1.0.dist-info/licenses/LICENSE
phoebusgen-3.1.0.dist-info/METADATA
phoebusgen-3.1.0.dist-info/WHEEL
phoebusgen-3.1.0.dist-info/top_level.txt
phoebusgen-3.1.0.dist-info/RECORD
