Metadata-Version: 2.4
Name: phoebusgen
Version: 3.1.0
Summary: Screen generator for CS-Studio Phoebus displays
Author-email: Tynan Ford <tford@lbl.gov>, Madeline Park <MadelinePark@lbl.gov>
License: 		    GNU GENERAL PUBLIC LICENSE
Project-URL: Homepage, https://github.com/als-epics/phoebusgen
Project-URL: Documentation, https://als-epics.github.io/phoebusgen
Project-URL: Repository, https://github.com/als-epics/phoebusgen
Project-URL: Bug Tracker, https://github.com/als-epics/phoebusgen/issues
Project-URL: Changelog, https://github.com/als-epics/phoebusgen/blob/master/CHANGELOG.md
Classifier: Programming Language :: Python :: 3
Classifier: License :: OSI Approved :: GNU General Public License v2 (GPLv2)
Classifier: Operating System :: OS Independent
Classifier: Development Status :: 5 - Production/Stable
Classifier: Topic :: Software Development :: Code Generators
Requires-Python: >=3.5
License-File: LICENSE
Provides-Extra: dev
Requires-Dist: pre-commit; extra == "dev"
Provides-Extra: docs
Requires-Dist: sphinx; extra == "docs"
Requires-Dist: sphinx_rtd_theme; extra == "docs"
Requires-Dist: sphinx_autodoc_typehints; extra == "docs"
Dynamic: license-file
